sql_scheduler/__init__.py
sql_scheduler/_constants.py
sql_scheduler/_helpers.py
sql_scheduler/cli.py
sql_scheduler/exceptions.py
sql_scheduler/orchestrator.py
sql_scheduler/py.typed
sql_scheduler/sql_scheduler.py
sql_scheduler/sql_task.py
sql_scheduler-0.3.2.dist-info/LICENSE.md
sql_scheduler-0.3.2.dist-info/METADATA
sql_scheduler-0.3.2.dist-info/WHEEL
sql_scheduler-0.3.2.dist-info/entry_points.txt
sql_scheduler-0.3.2.dist-info/top_level.txt
sql_scheduler-0.3.2.dist-info/RECORD
