Metadata-Version: 2.1
Name: sql-scheduler
Version: 0.3.2
Summary: sql-scheduler allows you to easily run a suite of SQL scripts against a Postgres/Redshift database.
Home-page: https://github.com/henryivesjones/sql-scheduler
Author: Henry Jones
Author-email: Henry Jones <henryivesjones@gmail.com>
License: GPL-3.0-or-later
Keywords: sql,postgres,scheduler,redshift
Classifier: License :: OSI Approved :: GNU General Public License v3 or later (GPLv3+)
Classifier: Programming Language :: Python :: 3
Classifier: Programming Language :: Python :: 3.7
Classifier: Programming Language :: Python :: 3.8
Classifier: Programming Language :: Python :: 3.9
Classifier: Programming Language :: Python :: 3.10
Classifier: Programming Language :: Python :: 3.11
Requires-Python: >=3.6
License-File: LICENSE.md
Requires-Dist: asyncpg
Requires-Dist: python-dateutil
Requires-Dist: click (>=8)
